dojot/module/__init__.py
dojot/module/auth.py
dojot/module/config.py
dojot/module/http_requester.py
dojot/module/logger.py
dojot/module/messenger.py
dojot/module/kafka/__init__.py
dojot/module/kafka/consumer.py
dojot/module/kafka/producer.py
dojot/module/kafka/topic_manager.py
dojot.module-0.2.4.dist-info/LICENSE
dojot.module-0.2.4.dist-info/METADATA
dojot.module-0.2.4.dist-info/NOTICE
dojot.module-0.2.4.dist-info/WHEEL
dojot.module-0.2.4.dist-info/top_level.txt
dojot.module-0.2.4.dist-info/RECORD
